pycot/__init__.py
pycot/cesium.py
pycot/cot.py
pycot/example.xml
pycot/geo.py
pycot/models.py
pycot/parser.py
pycot/writer.py
pycot_tak-0.0.4.dist-info/licenses/LICENSE
pycot_tak-0.0.4.dist-info/METADATA
pycot_tak-0.0.4.dist-info/WHEEL
pycot_tak-0.0.4.dist-info/entry_points.txt
pycot_tak-0.0.4.dist-info/top_level.txt
pycot_tak-0.0.4.dist-info/RECORD
