Metadata-Version: 2.4
Name: PyCoT-tak
Version: 0.0.4
Summary: PyCoT: Python Cursor-on-Target toolkit (node-CoT style) with XML->CoTEvent, GeoJSON, Cesium conversion capabilities
Author: COASsoft
Author-email: Oscar Aguilar Ramos <aguilardeciudad@gmail.com>
Project-URL: Homepage, https://github.com/COASsoft/PyCoT
Project-URL: Repository, https://github.com/COASsoft/PyCoT
Project-URL: Issues, https://github.com/COASsoft/PyCoT/issues
Project-URL: Documentation, https://github.com/COASsoft/PyCoT
Keywords: TAK,ATAK,CoT,Cursor on Target,GIS,GeoJSON,Cesium,XML,Parsing,Data Conversion
Classifier: Development Status :: 4 - Beta
Classifier: Intended Audience :: Developers
Classifier: Intended Audience :: Science/Research
Classifier: License :: OSI Approved :: MIT License
Classifier: Operating System :: OS Independent
Classifier: Programming Language :: Python :: 3
Classifier: Programming Language :: Python :: 3.9
Classifier: Programming Language :: Python :: 3.10
Classifier: Programming Language :: Python :: 3.11
Classifier: Programming Language :: Python :: 3.12
Classifier: Topic :: Internet
Classifier: Topic :: Scientific/Engineering :: GIS
Classifier: Topic :: Software Development :: Libraries :: Python Modules
Classifier: Topic :: Text Processing :: Markup :: XML
Requires-Python: >=3.9
License-File: LICENSE
Requires-Dist: lxml>=5.0.0
Requires-Dist: pydantic>=2.0.0
Requires-Dist: typing-extensions>=4.0.0
Provides-Extra: speed
Requires-Dist: lxml>=5.0.0; extra == "speed"
Requires-Dist: orjson>=3.0.0; extra == "speed"
Provides-Extra: ws
Requires-Dist: websockets>=12.0.0; extra == "ws"
Provides-Extra: proto
Requires-Dist: takproto>=0.3.0; extra == "proto"
Provides-Extra: dev
Requires-Dist: pytest>=7.0.0; extra == "dev"
Requires-Dist: pytest-asyncio>=0.21.0; extra == "dev"
Requires-Dist: pytest-cov>=4.0.0; extra == "dev"
Requires-Dist: black>=23.0.0; extra == "dev"
Requires-Dist: isort>=5.12.0; extra == "dev"
Requires-Dist: mypy>=1.0.0; extra == "dev"
Requires-Dist: ruff>=0.1.0; extra == "dev"
Provides-Extra: docs
Requires-Dist: mkdocs>=1.5.0; extra == "docs"
Requires-Dist: mkdocs-material>=9.0.0; extra == "docs"
Requires-Dist: mkdocstrings[python]>=0.20.0; extra == "docs"
Dynamic: license-file
